libprofileinfo_extractor.so
mirax_profileinfo_extractor-0.2.4.dist-info/RECORD
mirax_profileinfo_extractor-0.2.4.dist-info/WHEEL
mirax_profileinfo_extractor-0.2.4.dist-info/LICENSE
mirax_profileinfo_extractor-0.2.4.dist-info/top_level.txt
mirax_profileinfo_extractor-0.2.4.dist-info/METADATA
mirax_profileinfo_extractor/__init__.py
mirax_profileinfo_extractor/extractor.py
